README.md
setup.py
src/swergio_toolbox/__init__.py
src/swergio_toolbox/objects.py
src/swergio_toolbox/swarm_control.py
src/swergio_toolbox.egg-info/PKG-INFO
src/swergio_toolbox.egg-info/SOURCES.txt
src/swergio_toolbox.egg-info/dependency_links.txt
src/swergio_toolbox.egg-info/requires.txt
src/swergio_toolbox.egg-info/top_level.txt