Metadata-Version: 2.1
Name: swergio-toolbox
Version: 0.0.2
Summary: Swergio Toolbox Package
Home-page: https://github.com/swergio/toolbox
Author: Ishmagurca
License: UNKNOWN
Platform: UNKNOWN
Classifier: Programming Language :: Python :: 3
Classifier: Operating System :: OS Independent
Requires-Python: >=3.6
